aidkitcli/__init__.py
aidkitcli/config.py
aidkitcli/analysis/__init__.py
aidkitcli/analysis/__main__.py
aidkitcli/analysis/comprehensibility/__init__.py
aidkitcli/analysis/comprehensibility/gradient_map.py
aidkitcli/analysis/functionality/__init__.py
aidkitcli/analysis/functionality/data_investigation.py
aidkitcli/analysis/functionality/performance.py
aidkitcli/analysis/robustness/__init__.py
aidkitcli/analysis/robustness/aggregated_constant.py
aidkitcli/analysis/robustness/aggregated_relative_constant.py
aidkitcli/analysis/robustness/blackbox.py
aidkitcli/analysis/robustness/cdc.py
aidkitcli/analysis/robustness/constant.py
aidkitcli/analysis/robustness/correlation.py
aidkitcli/analysis/robustness/evolution_mixed.py
aidkitcli/analysis/robustness/fgsm.py
aidkitcli/analysis/robustness/increase.py
aidkitcli/analysis/robustness/kri.py
aidkitcli/analysis/robustness/peak.py
aidkitcli/analysis/robustness/random.py
aidkitcli/analysis/robustness/relative_constant.py
aidkitcli/authenticate/__init__.py
aidkitcli/authenticate/__main__.py
aidkitcli/core/__init__.py
aidkitcli/core/execute_analysis.py
aidkitcli/core/report.py
aidkitcli/core/request_model.py
aidkitcli/core/status.py
aidkitcli/core/stored_model.py
aidkitcli/core/utils.py
aidkitcli/core/analyses/__init__.py
aidkitcli/core/analyses/aggregated_constant.py
aidkitcli/core/analyses/aggregated_relative_constant.py
aidkitcli/core/analyses/blackbox.py
aidkitcli/core/analyses/cdc.py
aidkitcli/core/analyses/constant.py
aidkitcli/core/analyses/correlation.py
aidkitcli/core/analyses/data_investigation.py
aidkitcli/core/analyses/evolution_mixed.py
aidkitcli/core/analyses/fgsm.py
aidkitcli/core/analyses/gradient_map.py
aidkitcli/core/analyses/increase.py
aidkitcli/core/analyses/kri.py
aidkitcli/core/analyses/peak.py
aidkitcli/core/analyses/performance.py
aidkitcli/core/analyses/random.py
aidkitcli/core/analyses/relative_constant.py
aidkitcli/data/__init__.py
aidkitcli/data/__main__.py
aidkitcli/data_access/__init__.py
aidkitcli-0.2.31.dist-info/METADATA
aidkitcli-0.2.31.dist-info/WHEEL
aidkitcli-0.2.31.dist-info/top_level.txt
aidkitcli-0.2.31.dist-info/RECORD
