Metadata-Version: 2.1
Name: aidkitcli
Version: 0.2.31
Summary: aidkit, the first aid kit for AI development, verification & validation. The AI-debugging &-boosting toolkit is both the embodiment of quality standards, as well as the plug & play tool for AI developers who want to put their model through its paces in every section of the AI lifecycle to reduce costs / iterations. 
Home-page: https://aidkit.ai/
Author: neurocat GmbH
Author-email: dev@neurocat.ai
License: MIT
Platform: UNKNOWN
Requires-Dist: pandas (==1.2.4)
Requires-Dist: pytest (==6.1.0)
Requires-Dist: requests (==2.24.0)
Requires-Dist: Sphinx (==3.5.2)
Requires-Dist: sphinx-rtd-theme (==0.5.1)
